molcas_suite/__init__.py
molcas_suite/__version__.py
molcas_suite/cli.py
molcas_suite/extractor.py
molcas_suite/generate_input.py
molcas_suite/generate_job.py
molcas_suite/h5tools.py
molcas_suite/orbs.py
molcas_suite-1.37.1.dist-info/licenses/LICENSE
molcas_suite-1.37.1.dist-info/METADATA
molcas_suite-1.37.1.dist-info/WHEEL
molcas_suite-1.37.1.dist-info/entry_points.txt
molcas_suite-1.37.1.dist-info/top_level.txt
molcas_suite-1.37.1.dist-info/RECORD
