Metadata-Version: 2.4
Name: molcas_suite
Version: 1.37.1
Summary: A package for dealing with OpenMOLCAS input and output files
Home-page: https://gitlab.com/chilton-group/molcas_suite
Author: Chilton Group
Author-email: nicholas.chilton@manchester.ac.uk
Project-URL: Bug Tracker, https://gitlab.com/chilton-group/molcas_suite/-/issues
Project-URL: Documentation, https://chilton-group.gitlab.io/molcas_suite
Classifier: Programming Language :: Python :: 3
Classifier: License :: OSI Approved :: GNU General Public License v3 (GPLv3)
Classifier: Operating System :: OS Independent
Requires-Python: >=3.9
License-File: LICENSE
Requires-Dist: numpy
Requires-Dist: scipy
Requires-Dist: h5py
Requires-Dist: xyz_py>=5.11.0
Requires-Dist: hpc_suite>=1.8.0
Requires-Dist: matplotlib
Dynamic: author
Dynamic: author-email
Dynamic: classifier
Dynamic: description
Dynamic: description-content-type
Dynamic: home-page
Dynamic: license-file
Dynamic: project-url
Dynamic: requires-dist
Dynamic: requires-python
Dynamic: summary
